wtfami/__init__.py
wtfami-0.1.0.dist-info/METADATA
wtfami-0.1.0.dist-info/WHEEL
wtfami-0.1.0.dist-info/top_level.txt
wtfami-0.1.0.dist-info/RECORD
