Metadata-Version: 2.4
Name: wtfami
Version: 0.1.0
Summary: A simple library to get the current path.
Home-page: https://pypi.org/
Author: 地灯dideng
Author-email: 3483434955@qq.com
Classifier: Programming Language :: Python :: 3
Classifier: License :: OSI Approved :: MIT License
Classifier: Operating System :: OS Independent
Requires-Python: >=3.6
Dynamic: author
Dynamic: author-email
Dynamic: classifier
Dynamic: description
Dynamic: description-content-type
Dynamic: home-page
Dynamic: requires-python
Dynamic: summary
